juqueue/__init__.py
juqueue/config.py
juqueue/exceptions.py
juqueue/logger.py
juqueue/models.py
juqueue/api/__init__.py
juqueue/api/app.py
juqueue/api/utils.py
juqueue/api/websocket.py
juqueue/api/cluster/__init__.py
juqueue/api/cluster/cluster.py
juqueue/api/experiments/__init__.py
juqueue/api/experiments/experiment.py
juqueue/api/experiments/run.py
juqueue/api/juqueue/__init__.py
juqueue/api/juqueue/reload.py
juqueue/api/juqueue/stop_server.py
juqueue/assets/__init__.py
juqueue/assets/juqueue_web/3rdpartylicenses.txt
juqueue/assets/juqueue_web/__init__.py
juqueue/assets/juqueue_web/index.html
juqueue/assets/juqueue_web/main.e967cc98d4540496.js
juqueue/assets/juqueue_web/polyfills.98fd45502fd70d1b.js
juqueue/assets/juqueue_web/runtime.9cfcb0ca6fe594da.js
juqueue/assets/juqueue_web/styles.f8e3132b35359c87.css
juqueue/backend/__init__.py
juqueue/backend/backend.py
juqueue/backend/run_instance.py
juqueue/backend/utils.py
juqueue/backend/clusters/__init__.py
juqueue/backend/clusters/cluster_manager.py
juqueue/backend/clusters/run_schedule.py
juqueue/backend/clusters/scaling_policy.py
juqueue/backend/clusters/utils.py
juqueue/backend/experiments/__init__.py
juqueue/backend/experiments/experiment_manager.py
juqueue/backend/nodes/__init__.py
juqueue/backend/nodes/executor.py
juqueue/backend/nodes/node_manager.py
juqueue/backend/nodes/node_manager_wrapper.py
juqueue/backend/nodes/slot.py
juqueue/backend/nodes/watchers.py
juqueue/definitions/__init__.py
juqueue/definitions/executor.py
juqueue/definitions/experiment.py
juqueue/definitions/path.py
juqueue/definitions/run.py
juqueue/definitions/utils.py
juqueue/definitions/cluster/__init__.py
juqueue/definitions/cluster/base.py
juqueue/definitions/cluster/local.py
juqueue/definitions/cluster/slurm.py
juqueue_bin/__init__.py
juqueue_bin/main.py
juqueue_web/.gitignore
juqueue_web/generate.sh
juqueue_web/openapi.json
juqueue_web/package-lock.json
juqueue_web/package.json
juqueue_web/juqueue-web/.browserslistrc
juqueue-0.0.15.dist-info/LICENSE
juqueue-0.0.15.dist-info/METADATA
juqueue-0.0.15.dist-info/WHEEL
juqueue-0.0.15.dist-info/entry_points.txt
juqueue-0.0.15.dist-info/top_level.txt
juqueue-0.0.15.dist-info/RECORD
