Metadata-Version: 2.1
Name: juqueue
Version: 0.0.15
Summary: Computation and work management system for time-constrained cluster environments.
Author-email: Viet Anh Khoa Tran <v.tran@fz-juelich.de>
License: GNU General Public License v3 (GPLv3)
Project-URL: Homepage, https://github.com/tran-khoa/JuQueue
Keywords: workflow,cluster,management,slurm,dask
Classifier: License :: OSI Approved :: GNU General Public License v3 (GPLv3)
Classifier: Development Status :: 2 - Pre-Alpha
Classifier: Operating System :: POSIX :: Linux
Classifier: Programming Language :: Python
Classifier: Programming Language :: Python :: 3
Requires-Python: >=3.7
License-File: LICENSE
Requires-Dist: pyyaml (~=6.0)
Requires-Dist: dask-jobqueue
Requires-Dist: dask (~=2022.5.2)
Requires-Dist: tornado (~=6.1)
Requires-Dist: loguru (~=0.6.0)
Requires-Dist: nest-asyncio
Requires-Dist: filelock (~=3.7.1)
Requires-Dist: fastapi (~=0.78.0)
Requires-Dist: hypercorn (~=0.13.2)
Requires-Dist: pydantic (~=1.9.1)
Requires-Dist: uvloop (~=0.16.0)
Requires-Dist: aioconsole
Provides-Extra: dev
Requires-Dist: bumpver ; extra == 'dev'
Requires-Dist: pip-tools ; extra == 'dev'
